protobuf_testing/__init__.py
protobuf_testing/tests/test_auto_factory.py
ucam_protobuf_testing-0.2.0.dist-info/LICENSE
ucam_protobuf_testing-0.2.0.dist-info/METADATA
ucam_protobuf_testing-0.2.0.dist-info/WHEEL
ucam_protobuf_testing-0.2.0.dist-info/RECORD
