Metadata-Version: 2.3
Name: ucam-protobuf-testing
Version: 0.2.0
Summary: Testing support library for python protobuf projects
License: MIT
Author: University of Cambridge Information Services
Author-email: devops-wilson@uis.cam.ac.uk
Requires-Python: >=3.10,<4.0
Classifier: Development Status :: 3 - Alpha
Classifier: Intended Audience :: Developers
Classifier: License :: OSI Approved :: MIT License
Classifier: Operating System :: OS Independent
Classifier: Programming Language :: Python :: 3
Classifier: Programming Language :: Python :: 3.10
Classifier: Programming Language :: Python :: 3.11
Classifier: Programming Language :: Python :: 3.12
Classifier: Programming Language :: Python :: 3.13
Requires-Dist: factory-boy (>=3.3.3,<4.0.0)
Project-URL: Repository, https://gitlab.developers.cam.ac.uk/uis/devops/lib/ucam-protobuf-testing-python
